{
    "categories": [
        {
            "id": "art_style_rendering",
            "name": "アートスタイル・レンダリング",
            "parent_id": "general",
            "tags": []
        },
        {
            "id": "painting_styles",
            "name": "絵画スタイル",
            "parent_id": "art_style_rendering",
            "tags": [
                {"en": "oil painting", "ja": "油絵"},
                {"en": "watercolor painting", "ja": "水彩画"},
                {"en": "acrylic painting", "ja": "アクリル画"},
                {"en": "gouache painting", "ja": "ガッシュ画"},
                {"en": "tempera painting", "ja": "テンペラ画"},
                {"en": "fresco", "ja": "フレスコ画"},
                {"en": "mural painting", "ja": "壁画"},
                {"en": "encaustic painting", "ja": "エンカウスティーク画"},
                {"en": "sumi-e", "ja": "水墨画"},
                {"en": "nihonga", "ja": "日本画"},
                {"en": "ukiyo-e", "ja": "浮世絵"},
                {"en": "ink wash painting", "ja": "墨絵"},
                {"en": "calligraphy", "ja": "書道"},
                {"en": "impressionism", "ja": "印象派"},
                {"en": "post-impressionism", "ja": "ポスト印象派"},
                {"en": "expressionism", "ja": "表現主義"},
                {"en": "surrealism", "ja": "シュルレアリスム"},
                {"en": "cubism", "ja": "キュビズム"},
                {"en": "abstract expressionism", "ja": "抽象表現主義"},
                {"en": "pop art", "ja": "ポップアート"},
                {"en": "minimalism (art)", "ja": "ミニマリズム (美術)"},
                {"en": "maximalism (art)", "ja": "マキシマリズム (美術)"},
                {"en": "baroque", "ja": "バロック"},
                {"en": "rococo", "ja": "ロココ"},
                {"en": "neoclassicism", "ja": "新古典主義"},
                {"en": "romanticism (art)", "ja": "ロマン主義 (美術)"},
                {"en": "gothic (art)", "ja": "ゴシック (美術)"},
                {"en": "renaissance (art)", "ja": "ルネサンス (美術)"},
                {"en": "medieval (art)", "ja": "中世 (美術)"},
                {"en": "byzantine (art)", "ja": "ビザンチン (美術)"},
                {"en": "art nouveau", "ja": "アール・ヌーヴォー"},
                {"en": "art deco", "ja": "アール・デコ"},
                {"en": "futurism (art)", "ja": "未来派 (美術)"},
                {"en": "constructivism", "ja": "構成主義"},
                {"en": "suprematism", "ja": "シュプレマティスム"},
                {"en": "de stijl", "ja": "デ・ステイル"},
                {"en": "bauhaus", "ja": "バウハウス"},
                {"en": "dadaism", "ja": "ダダイズム"},
                {"en": "fauvism", "ja": "フォーヴィスム"},
                {"en": "pointillism", "ja": "点描主義"},
                {"en": "divisionism", "ja": "分割主義"},
                {"en": "symbolism (art)", "ja": "象徴主義 (美術)"},
                {"en": "art brut", "ja": "アール・ブリュット"},
                {"en": "naive art", "ja": "素朴派"},
                {"en": "folk art", "ja": "フォークアート"},
                {"en": "outsider art", "ja": "アウトサイダーアート"},
                {"en": "street art", "ja": "ストリートアート"},
                {"en": "graffiti art", "ja": "グラフィティアート"},
                {"en": "mural art", "ja": "壁画アート"},
                {"en": "body painting", "ja": "ボディペインティング"},
                {"en": "face painting", "ja": "フェイスペインティング"},
                {"en": "digital painting", "ja": "デジタルペインティング"},
                {"en": "matte painting", "ja": "マットペインティング"},
                {"en": "concept art", "ja": "コンセプトアート"},
                {"en": "illustration", "ja": "イラストレーション"},
                {"en": "comic art", "ja": "コミックアート"},
                {"en": "manga art", "ja": "漫画アート"},
                {"en": "anime art", "ja": "アニメアート"},
                {"en": "cartoon art", "ja": "カートゥーンアート"},
                {"en": "storybook illustration", "ja": "絵本イラスト"},
                {"en": "children's book illustration", "ja": "児童書イラスト"},
                {"en": "scientific illustration", "ja": "科学イラスト"},
                {"en": "technical illustration", "ja": "テクニカルイラスト"},
                {"en": "fashion illustration", "ja": "ファッションイラスト"},
                {"en": "architectural illustration", "ja": "建築イラスト"},
                {"en": "medical illustration", "ja": "医療イラスト"},
                {"en": "botanical illustration", "ja": "植物イラスト"},
                {"en": "zoological illustration", "ja": "動物イラスト"},
                {"en": "fantasy art", "ja": "ファンタジーアート"},
                {"en": "sci-fi art", "ja": "SFアート"},
                {"en": "horror art", "ja": "ホラーアート"},
                {"en": "surreal art", "ja": "シュールアート"},
                {"en": "abstract art", "ja": "抽象芸術"},
                {"en": "realistic art", "ja": "写実的なアート"},
                {"en": "stylized art", "ja": "様式化されたアート"},
                {"en": "hyperrealism", "ja": "ハイパーリアリズム"},
                {"en": "photorealism", "ja": "フォトリアリズム"},
                {"en": "superrealism", "ja": "スーパーリアリズム"}
            ]
        },
        {
            "id": "drawing_sketching_styles",
            "name": "描画・スケッチスタイル",
            "parent_id": "art_style_rendering",
            "tags": [
                {"en": "pencil sketch", "ja": "鉛筆スケッチ"},
                {"en": "charcoal drawing", "ja": "木炭画"},
                {"en": "ink drawing", "ja": "インク画"},
                {"en": "pen and ink", "ja": "ペン画"},
                {"en": "marker drawing", "ja": "マーカー画"},
                {"en": "pastel drawing", "ja": "パステル画"},
                {"en": "conte crayon", "ja": "コンテ画"},
                {"en": "silverpoint", "ja": "シルバーポイント"},
                {"en": "etching", "ja": "エッチング"},
                {"en": "engraving", "ja": "彫刻"},
                {"en": "lithography", "ja": "リトグラフ"},
                {"en": "woodcut", "ja": "木版画"},
                {"en": "linocut", "ja": "リノカット"},
                {"en": "mezzotint", "ja": "メゾティント"},
                {"en": "aquatint", "ja": "アクアティント"},
                {"en": "drypoint", "ja": "ドライポイント"},
                {"en": "monotype", "ja": "モノタイプ"},
                {"en": "screen printing", "ja": "シルクスクリーン印刷"},
                {"en": "digital drawing", "ja": "デジタルドローイング"},
                {"en": "line art", "ja": "線画"},
                {"en": "cross-hatching", "ja": "クロスハッチング"},
                {"en": "stippling", "ja": "点描"},
                {"en": "hatching", "ja": "ハッチング"},
                {"en": "scribble", "ja": "落書き"},
                {"en": "doodle", "ja": "いたずら書き"},
                {"en": "technical drawing", "ja": "製図"},
                {"en": "architectural drawing", "ja": "建築図面"},
                {"en": "engineering drawing", "ja": "工学図面"},
                {"en": "blueprint", "ja": "青写真"},
                {"en": "schematic", "ja": "回路図"},
                {"en": "diagram", "ja": "図"},
                {"en": "chart", "ja": "図表"},
                {"en": "map", "ja": "地図"},
                {"en": "plan", "ja": "計画図"},
                {"en": "layout", "ja": "レイアウト"},
                {"en": "wireframe", "ja": "ワイヤーフレーム"},
                {"en": "storyboard", "ja": "絵コンテ"},
                {"en": "comic strip", "ja": "漫画のコマ"},
                {"en": "graphic novel", "ja": "グラフィックノベル"},
                {"en": "manga", "ja": "漫画"},
                {"en": "webtoon", "ja": "ウェブトゥーン"},
                {"en": "sketchbook", "ja": "スケッチブック"},
                {"en": "drawing pad", "ja": "ドローイングパッド"},
                {"en": "canvas (drawing)", "ja": "キャンバス (描画)"},
                {"en": "paper", "ja": "紙"},
                {"en": "parchment", "ja": "羊皮紙"},
                {"en": "vellum", "ja": "ベラム"},
                {"en": "papyrus", "ja": "パピルス"},
                {"en": "tablet (drawing)", "ja": "タブレット (描画)"},
                {"en": "digital canvas", "ja": "デジタルキャンバス"},
                {"en": "vector art", "ja": "ベクターアート"},
                {"en": "raster art", "ja": "ラスターアート"},
                {"en": "pixel art", "ja": "ピクセルアート"},
                {"en": "voxel art", "ja": "ボクセルアート"},
                {"en": "ascii art", "ja": "アスキーアート"},
                {"en": "emoji art", "ja": "絵文字アート"},
                {"en": "generative art", "ja": "ジェネラティブアート"},
                {"en": "algorithmic art", "ja": "アルゴリズミックアート"},
                {"en": "ai art", "ja": "AIアート"},
                {"en": "neural network art", "ja": "ニューラルネットワークアート"},
                {"en": "deep learning art", "ja": "深層学習アート"},
                {"en": "machine learning art", "ja": "機械学習アート"},
                {"en": "glitch art", "ja": "グリッチアート"},
                {"en": "datamoshing", "ja": "データモッシング"},
                {"en": "circuit bending", "ja": "サーキットベンディング"},
                {"en": "fractal art", "ja": "フラクタルアート"},
                {"en": "mandala art", "ja": "マンダラアート"},
                {"en": "zentangle", "ja": "ゼンタングル"},
                {"en": "doodle art", "ja": "落書きアート"}
            ]
        },
        {
            "id": "digital_art_styles",
            "name": "デジタルアートスタイル",
            "parent_id": "art_style_rendering",
            "tags": [
                {"en": "digital painting", "ja": "デジタルペインティング"},
                {"en": "vector art", "ja": "ベクターアート"},
                {"en": "pixel art", "ja": "ピクセルアート"},
                {"en": "voxel art", "ja": "ボクセルアート"},
                {"en": "3d rendering", "ja": "3Dレンダリング"},
                {"en": "cgi (computer generated imagery)", "ja": "CGI (コンピュータ生成画像)"},
                {"en": "vfx (visual effects)", "ja": "VFX (視覚効果)"},
                {"en": "motion graphics", "ja": "モーショングラフィックス"},
                {"en": "animation", "ja": "アニメーション"},
                {"en": "2d animation", "ja": "2Dアニメーション"},
                {"en": "3d animation", "ja": "3Dアニメーション"},
                {"en": "stop motion animation", "ja": "ストップモーションアニメーション"},
                {"en": "rotoscoping", "ja": "ロトスコープ"},
                {"en": "cel animation", "ja": "セルアニメーション"},
                {"en": "anime style", "ja": "アニメ風"},
                {"en": "manga style", "ja": "漫画風"},
                {"en": "cartoon style", "ja": "カートゥーン風"},
                {"en": "comic book style", "ja": "コミック風"},
                {"en": "game art", "ja": "ゲームアート"},
                {"en": "concept art (digital)", "ja": "コンセプトアート (デジタル)"},
                {"en": "matte painting (digital)", "ja": "マットペインティング (デジタル)"},
                {"en": "photo manipulation", "ja": "写真加工"},
                {"en": "compositing", "ja": "合成"},
                {"en": "digital collage", "ja": "デジタルコラージュ"},
                {"en": "generative art", "ja": "ジェネラティブアート"},
                {"en": "algorithmic art", "ja": "アルゴリズミックアート"},
                {"en": "ai art", "ja": "AIアート"},
                {"en": "neural network art", "ja": "ニューラルネットワークアート"},
                {"en": "deep learning art", "ja": "深層学習アート"},
                {"en": "machine learning art", "ja": "機械学習アート"},
                {"en": "glitch art", "ja": "グリッチアート"},
                {"en": "datamoshing", "ja": "データモッシング"},
                {"en": "fractal art", "ja": "フラクタルアート"},
                {"en": "digital sculpture", "ja": "デジタル彫刻"},
                {"en": "3d modeling", "ja": "3Dモデリング"},
                {"en": "texturing", "ja": "テクスチャリング"},
                {"en": "lighting (3d)", "ja": "ライティング (3D)"},
                {"en": "rendering (3d)", "ja": "レンダリング (3D)"},
                {"en": "rigging", "ja": "リギング"},
                {"en": "animation (3d)", "ja": "アニメーション (3D)"},
                {"en": "simulation", "ja": "シミュレーション"},
                {"en": "fluid simulation", "ja": "流体シミュレーション"},
                {"en": "cloth simulation", "ja": "布シミュレーション"},
                {"en": "hair simulation", "ja": "髪シミュレーション"},
                {"en": "particle effects", "ja": "パーティクルエフェクト"},
                {"en": "volumetric lighting", "ja": "ボリュメトリックライティング"},
                {"en": "global illumination", "ja": "大域照明"},
                {"en": "ambient occlusion", "ja": "アンビエントオクルージョン"},
                {"en": "bloom (rendering)", "ja": "ブルーム (レンダリング)"},
                {"en": "lens flare (rendering)", "ja": "レンズフレア (レンダリング)"},
                {"en": "chromatic aberration (rendering)", "ja": "色収差 (レンダリング)"},
                {"en": "vignetting (rendering)", "ja": "周辺減光 (レンダリング)"},
                {"en": "depth of field (rendering)", "ja": "被写界深度 (レンダリング)"},
                {"en": "motion blur (rendering)", "ja": "モーションブラー (レンダリング)"},
                {"en": "anti-aliasing", "ja": "アンチエイリアシング"},
                {"en": "texture filtering", "ja": "テクスチャフィルタリング"},
                {"en": "anisotropic filtering", "ja": "異方性フィルタリング"},
                {"en": "mipmap", "ja": "ミップマップ"},
                {"en": "normal mapping", "ja": "ノーマルマッピング"},
                {"en": "displacement mapping", "ja": "ディスプレイスメントマッピング"},
                {"en": "bump mapping", "ja": "バンプマッピング"},
                {"en": "specular mapping", "ja": "スペキュラーマッピング"},
                {"en": "roughness mapping", "ja": "ラフネスマッピング"},
                {"en": "metallic mapping", "ja": "メタリックマッピング"},
                {"en": "ambient occlusion mapping", "ja": "アンビエントオクルージョンマッピング"},
                {"en": "subsurface scattering", "ja": "サブサーフェススキャタリング"},
                {"en": "ray tracing", "ja": "レイトレーシング"},
                {"en": "path tracing", "ja": "パストレーシング"},
                {"en": "rasterization", "ja": "ラスタライズ"},
                {"en": "polygon count", "ja": "ポリゴン数"},
                {"en": "vertex count", "ja": "頂点数"},
                {"en": "texture resolution", "ja": "テクスチャ解像度"},
                {"en": "render farm", "ja": "レンダーファーム"},
                {"en": "gpu rendering", "ja": "GPUレンダリング"},
                {"en": "cpu rendering", "ja": "CPUレンダリング"},
                {"en": "real-time rendering", "ja": "リアルタイムレンダリング"},
                {"en": "offline rendering", "ja": "オフラインレンダリング"},
                {"en": "photorealistic rendering", "ja": "フォトリアルなレンダリング"},
                {"en": "stylized rendering", "ja": "様式化されたレンダリング"},
                {"en": "toon rendering", "ja": "トゥーンレンダリング"},
                {"en": "cel shading", "ja": "セルシェーディング"},
                {"en": "flat shading", "ja": "フラットシェーディング"},
                {"en": "smooth shading", "ja": "スムーズシェーディング"},
                {"en": "wireframe rendering", "ja": "ワイヤーフレームレンダリング"},
                {"en": "point cloud rendering", "ja": "点群レンダリング"},
                {"en": "volume rendering", "ja": "ボリュームレンダリング"},
                {"en": "non-photorealistic rendering (npr)", "ja": "非写実的レンダリング (NPR)"}
            ]
        },
        {
            "id": "photography_styles",
            "name": "写真スタイル",
            "parent_id": "art_style_rendering",
            "tags": [
                {"en": "portrait photography", "ja": "ポートレート写真"},
                {"en": "landscape photography", "ja": "風景写真"},
                {"en": "street photography", "ja": "ストリート写真"},
                {"en": "documentary photography", "ja": "ドキュメンタリー写真"},
                {"en": "fashion photography", "ja": "ファッション写真"},
                {"en": "product photography", "ja": "製品写真"},
                {"en": "food photography", "ja": "料理写真"},
                {"en": "architectural photography", "ja": "建築写真"},
                {"en": "wildlife photography", "ja": "野生動物写真"},
                {"en": "macro photography", "ja": "マクロ写真"},
                {"en": "astrophotography", "ja": "天体写真"},
                {"en": "underwater photography", "ja": "水中写真"},
                {"en": "aerial photography", "ja": "航空写真"},
                {"en": "drone photography", "ja": "ドローン写真"},
                {"en": "black and white photography", "ja": "モノクロ写真"},
                {"en": "sepia photography", "ja": "セピア写真"},
                {"en": "vintage photography", "ja": "ヴィンテージ写真"},
                {"en": "retro photography", "ja": "レトロ写真"},
                {"en": "film photography", "ja": "フィルム写真"},
                {"en": "digital photography", "ja": "デジタル写真"},
                {"en": "hdr photography", "ja": "HDR写真"},
                {"en": "panoramic photography", "ja": "パノラマ写真"},
                {"en": "time-lapse photography", "ja": "タイムラプス写真"},
                {"en": "long exposure photography", "ja": "長時間露光写真"},
                {"en": "light painting", "ja": "ライトペインティング"},
                {"en": "slow motion photography", "ja": "スローモーション写真"},
                {"en": "high-speed photography", "ja": "ハイスピード写真"},
                {"en": "infrared photography", "ja": "赤外線写真"},
                {"en": "ultraviolet photography", "ja": "紫外線写真"},
                {"en": "x-ray photography", "ja": "X線写真"},
                {"en": "microscopy photography", "ja": "顕微鏡写真"},
                {"en": "forensic photography", "ja": "法医学写真"},
                {"en": "medical photography", "ja": "医療写真"},
                {"en": "scientific photography", "ja": "科学写真"},
                {"en": "photojournalism", "ja": "フォトジャーナリズム"},
                {"en": "fine art photography", "ja": "ファインアート写真"},
                {"en": "conceptual photography", "ja": "コンセプチュアル写真"},
                {"en": "abstract photography", "ja": "抽象写真"},
                {"en": "surreal photography", "ja": "シュール写真"},
                {"en": "minimalist photography", "ja": "ミニマリスト写真"},
                {"en": "maximalist photography", "ja": "マキシマリスト写真"},
                {"en": "candid photography", "ja": " candid写真"},
                {"en": "posed photography", "ja": "ポーズ写真"},
                {"en": "studio photography", "ja": "スタジオ写真"},
                {"en": "outdoor photography", "ja": "屋外写真"},
                {"en": "indoor photography", "ja": "屋内写真"},
                {"en": "natural light photography", "ja": "自然光写真"},
                {"en": "artificial light photography", "ja": "人工光写真"},
                {"en": "flash photography", "ja": "フラッシュ写真"},
                {"en": "strobe photography", "ja": "ストロボ写真"},
                {"en": "continuous lighting", "ja": "定常光"},
                {"en": "off-camera flash", "ja": "オフカメラフラッシュ"},
                {"en": "on-camera flash", "ja": "オンカメラフラッシュ"},
                {"en": "fill flash", "ja": "フィルフラッシュ"},
                {"en": "red-eye reduction", "ja": "赤目軽減"},
                {"en": "slow sync flash", "ja": "スロースシンクロフラッシュ"},
                {"en": "rear curtain sync", "ja": "後幕シンクロ"},
                {"en": "high-speed sync", "ja": "ハイスピードシンクロ"},
                {"en": "flash diffuser", "ja": "フラッシュディフューザー"},
                {"en": "softbox", "ja": "ソフトボックス"},
                {"en": "beauty dish", "ja": "ビューティーディッシュ"},
                {"en": "umbrella (photography)", "ja": "アンブレラ (写真)"},
                {"en": "reflector (photography)", "ja": "レフ板 (写真)"},
                {"en": "snoot", "ja": "スヌート"},
                {"en": "grid (photography)", "ja": "グリッド (写真)"},
                {"en": "barn doors", "ja": "バーンドア"},
                {"en": "gels (photography)", "ja": "ジェル (写真)"},
                {"en": "filters (photography)", "ja": "フィルター (写真)"},
                {"en": "polarizer filter", "ja": "偏光フィルター"},
                {"en": "nd filter", "ja": "NDフィルター"},
                {"en": "uv filter", "ja": "UVフィルター"},
                {"en": "protective filter", "ja": "保護フィルター"},
                {"en": "close-up filter", "ja": "クローズアップフィルター"},
                {"en": "star filter", "ja": "クロスフィルター"},
                {"en": "diffuser filter", "ja": "拡散フィルター"},
                {"en": "fog filter", "ja": "フォグフィルター"},
                {"en": "soft focus filter", "ja": "ソフトフォーカスフィルター"},
                {"en": "black mist filter", "ja": "ブラックミストフィルター"},
                {"en": "pro-mist filter", "ja": "プロミストフィルター"},
                {"en": "streak filter", "ja": "ストリークフィルター"},
                {"en": "kaleidoscope filter", "ja": "万華鏡フィルター"},
                {"en": "infrared filter", "ja": "赤外線フィルター"},
                {"en": "ultraviolet filter", "ja": "紫外線フィルター"},
                {"en": "color filter", "ja": "カラーフィルター"},
                {"en": "gradient filter", "ja": "グラデーションフィルター"},
                {"en": "reverse gradient filter", "ja": "リバースグラデーションフィルター"},
                {"en": "center spot filter", "ja": "センタースポットフィルター"},
                {"en": "split field filter", "ja": "スプリットフィールドフィルター"},
                {"en": "diopter filter", "ja": "ディオプターフィルター"},
                {"en": "fisheye attachment", "ja": "魚眼アタッチメント"},
                {"en": "wide-angle attachment", "ja": "広角アタッチメント"},
                {"en": "telephoto attachment", "ja": "望遠アタッチメント"},
                {"en": "macro attachment", "ja": "マクロアタッチメント"},
                {"en": "camera", "ja": "カメラ"},
                {"en": "dslr camera", "ja": "デジタル一眼レフカメラ"},
                {"en": "mirrorless camera", "ja": "ミラーレスカメラ"},
                {"en": "point and shoot camera", "ja": "コンパクトデジタルカメラ"},
                {"en": "smartphone camera", "ja": "スマートフォンカメラ"},
                {"en": "action camera", "ja": "アクションカメラ"},
                {"en": "360 camera", "ja": "360度カメラ"},
                {"en": "instant camera", "ja": "インスタントカメラ"},
                {"en": "film camera", "ja": "フィルムカメラ"},
                {"en": "medium format camera", "ja": "中判カメラ"},
                {"en": "large format camera", "ja": "大判カメラ"},
                {"en": "pinhole camera", "ja": "ピンホールカメラ"},
                {"en": "drone camera", "ja": "ドローンカメラ"},
                {"en": "underwater camera", "ja": "水中カメラ"},
                {"en": "security camera", "ja": "監視カメラ"},
                {"en": "webcam", "ja": "ウェブカメラ"},
                {"en": "dash cam", "ja": "ドライブレコーダー"},
                {"en": "body camera", "ja": "ボディカメラ"},
                {"en": "spy camera", "ja": "スパイカメラ"},
                {"en": "hidden camera", "ja": "隠しカメラ"},
                {"en": "disposable camera", "ja": "使い捨てカメラ"},
                {"en": "disposable film camera", "ja": "使い捨てフィルムカメラ"},
                {"en": "disposable digital camera", "ja": "使い捨てデジタルカメラ"},
                {"en": "polaroid camera", "ja": "ポラロイドカメラ"},
                {"en": "fujifilm instax", "ja": "富士フイルム instax"},
                {"en": "leica camera", "ja": "ライカカメラ"},
                {"en": "hasselblad camera", "ja": "ハッセルブラッドカメラ"},
                {"en": "canon camera", "ja": "キヤノンカメラ"},
                {"en": "nikon camera", "ja": "ニコンカメラ"},
                {"en": "sony camera", "ja": "ソニーカメラ"},
                {"en": "fujifilm camera", "ja": "富士フイルムカメラ"},
                {"en": "olympus camera", "ja": "オリンパスカメラ"},
                {"en": "panasonic camera", "ja": "パナソニックカメラ"},
                {"en": "pentax camera", "ja": "ペンタックスカメラ"},
                {"en": "sigma camera", "ja": "シグマカメラ"},
                {"en": "tamron lens", "ja": "タムロンレンズ"},
                {"en": "sigma lens", "ja": "シグマレンズ"},
                {"en": "tokina lens", "ja": "トキナーレンズ"},
                {"en": "zeiss lens", "ja": "ツァイスレンズ"},
                {"en": "voigtlander lens", "ja": "フォクトレンダーレンズ"},
                {"en": "samyang lens", "ja": "サムヤンレンズ"},
                {"en": "rokinon lens", "ja": "ロキノンレンズ"},
                {"en": "laowa lens", "ja": "ラオワレンズ"},
                {"en": "venus optics", "ja": "ヴィーナスオプティクス"},
                {"en": "lensbaby", "ja": "レンズベビー"},
                {"en": "holga camera", "ja": "ホルガカメラ"},
                {"en": "lomo camera", "ja": "ロモカメラ"},
                {"en": "toy camera", "ja": "トイカメラ"},
                {"en": "disposable camera effect", "ja": "使い捨てカメラ効果"},
                {"en": "film grain", "ja": "フィルムグレイン"},
                {"en": "noise (photography)", "ja": "ノイズ (写真)"},
                {"en": "digital noise", "ja": "デジタルノイズ"},
                {"en": "chroma noise", "ja": "クロマノイズ"},
                {"en": "luminance noise", "ja": "輝度ノイズ"},
                {"en": "hot pixels", "ja": "ホットピクセル"},
                {"en": "dead pixels", "ja": "デッドピクセル"},
                {"en": "stuck pixels", "ja": "スタックピクセル"},
                {"en": "banding", "ja": "バンディング"},
                {"en": "posterization", "ja": "ポスタリゼーション"},
                {"en": "color banding", "ja": "カラーバンディング"},
                {"en": "moire", "ja": "モアレ"},
                {"en": "aliasing", "ja": "エイリアシング"},
                {"en": "jaggies", "ja": "ジャギー"},
                {"en": "pixelation", "ja": "ピクセル化"},
                {"en": "compression artifacts", "ja": "圧縮アーティファクト"},
                {"en": "jpeg artifacts", "ja": "JPEGアーティファクト"},
                {"en": "ghosting (photography)", "ja": "ゴースト (写真)"},
                {"en": "flare (photography)", "ja": "フレア (写真)"},
                {"en": "haloing", "ja": "ハロ"},
                {"en": "fringing", "ja": "フリンジング"},
                {"en": "purple fringing", "ja": "パープルフリンジング"},
                {"en": "green fringing", "ja": "グリーンフリンジング"},
                {"en": "blue fringing", "ja": "ブルーフリンジング"},
                {"en": "red fringing", "ja": "レッドフリンジング"},
                {"en": "lens distortion", "ja": "レンズ歪曲"},
                {"en": "barrel distortion", "ja": "樽型歪曲"},
                {"en": "pincushion distortion", "ja": "糸巻き型歪曲"},
                {"en": "chromatic aberration", "ja": "色収差"},
                {"en": "spherical aberration", "ja": "球面収差"},
                {"en": "coma", "ja": "コマ収差"},
                {"en": "astigmatism", "ja": "非点収差"},
                {"en": "field curvature", "ja": "像面湾曲"},
                {"en": "vignetting", "ja": "周辺減光"},
                {"en": "hotspot (photography)", "ja": "ホットスポット (写真)"},
                {"en": "cold spot (photography)", "ja": "コールドスポット (写真)"},
                {"en": "blown out highlights", "ja": "ハイライトの白飛び"},
                {"en": "crushed blacks", "ja": "黒つぶれ"},
                {"en": "clipping (photography)", "ja": "クリッピング (写真)"},
                {"en": "banding (photography)", "ja": "バンディング (写真)"},
                {"en": "posterization (photography)", "ja": "ポスタリゼーション (写真)"},
                {"en": "color shift", "ja": "色ずれ"},
                {"en": "color cast", "ja": "色かぶり"},
                {"en": "color fringing", "ja": "色フリンジング"},
                {"en": "color noise", "ja": "カラーノイズ"},
                {"en": "luminance noise", "ja": "輝度ノイズ"},
                {"en": "digital artifacts", "ja": "デジタルアーティファクト"},
                {"en": "moire pattern", "ja": "モアレパターン"},
                {"en": "aliasing (photography)", "ja": "エイリアシング (写真)"},
                {"en": "jaggies (photography)", "ja": "ジャギー (写真)"},
                {"en": "pixelation (photography)", "ja": "ピクセル化 (写真)"},
                {"en": "compression artifacts (photography)", "ja": "圧縮アーティファクト (写真)"},
                {"en": "jpeg artifacts (photography)", "ja": "JPEGアーティファクト (写真)"}
            ]
        }
    ]
}
